{
  "tcin": "79555308",
  "name": "13&#34;x20&#34; Sunbrella Outdoor Throw Pillow Ruby: Hexagonal Dot Design, UV &#38; Weather-Resistant Acrylic, Polyester Fill",
  "brand": "",
  "price": "$61.00",
  "currency": "USD",
  "description": "The Ruby Outdoor Throw Pillow from Sunbrella makes a lovely, fresh addition to your summer decor. In an appealing shade of red and featuring an attractive dot design in a hexagonal pattern, this outdoor throw pillow elevates your outdoor ensemble while adding a little extra comfort to your surroundings. The weather-resistant fabric keeps it looking great season after season, and it's amply stuffed for a comfortable, supportive surface. Add it to a bank of pillows on your outdoor couch for a bold pop of color and pattern, or simply place it on a wicker side chair or lounger for a little extra comfort. Sunbrella is a 100% acrylic fabric that is water resistant, spill resistant, and fade resistant. Ideal for outdoor use, Sunbrella fabric is UV treated for high-quality fade resistance.",
  "categories": [
    "Outdoor Living & Garden",
    "Outdoor Decor",
    "Outdoor Cushions"
  ],
  "image_url": "https://target.scene7.com/is/image/Target/GUEST_b53bb261-34ab-436f-b048-5dd6f622264f",
  "glb_url": "https://digitalcontent.target.com/vault/1653955200/CLOUD_d6256b74-964a-47b0-91c4-fd506d6cffb6.glb",
  "product_url": "https://www.target.com/p/-/A-79555308",
  "dimensions": {
    "height": 0.508,
    "width": 0.3302,
    "depth": 0.127,
    "unit": "m",
    "source": "glb"
  }
}
