{
  "tcin": "94309263",
  "name": "14&#34;x72&#34; Reversible Menorah Table Runner - Spritz&#8482;",
  "brand": "Spritz",
  "price": "$15.30",
  "currency": "USD",
  "description": "Add a festive touch to your table with the 14\"x 72\" reversible Menorah table runner from Spritz™. One side features a playful menorah pattern while the other offers a simple solid for everyday use. It's a quick way to bring a bit of holiday cheer to your dining setup without overthinking it. Just lay it down, set your dishes and you're good to go.<br /><br />Spritz™: Pops of joy that make the moment™",
  "categories": [
    "Kitchen & Dining",
    "Kitchen & Table Linens",
    "Table Runners"
  ],
  "image_url": "https://target.scene7.com/is/image/Target/GUEST_408e422e-bc98-4205-bace-371809ac5b84",
  "glb_url": "https://digitalcontent.target.com/vault/1767830400/CLOUD_411048a9-ccab-475f-8f6e-65bbe969bb9d.glb",
  "product_url": "https://www.target.com/p/-/A-94309263",
  "dimensions": {
    "height": 1.8364,
    "width": 0.9313,
    "depth": 0.7711,
    "unit": "m",
    "source": "glb"
  }
}
