{
  "tcin": "90010023",
  "name": "19 fl oz Glass Bower Tall Tumbler Gray - Threshold&#8482;",
  "brand": "Threshold",
  "price": "$3.00",
  "currency": "USD",
  "description": "Bring an elegant touch to your drinkware with the 19-Fluid-Ounce Glass Bower Tall Tumbler from Threshold™. This tall tumbler features a see-through design for an elevated look. Made of glass, this gray tumbler is suitable for cold beverages. Best of all, it is dishwasher safe for easy cleanup.                                                                   Threshold™ Looks like home, feels like you.",
  "categories": [
    "Kitchen & Dining",
    "Glassware & Drinkware",
    "Drinking Glasses"
  ],
  "image_url": "https://target.scene7.com/is/image/Target/GUEST_c7882be5-3604-41ba-8a19-ee9634ee315f",
  "glb_url": "https://digitalcontent.target.com/vault/1716163200/CLOUD_026341d9-6c61-4cf3-a312-f8188bf76855.glb",
  "product_url": "https://www.target.com/p/-/A-90010023",
  "dimensions": {
    "height": 0.123,
    "width": 0.0866,
    "depth": 0.0866,
    "unit": "m",
    "source": "glb"
  },
  "color": "Gray",
  "color_source": "parsed"
}
