{
  "tcin": "94568983",
  "name": "22&#34;x30&#34; Ribbed Wood Wall Mirror - Threshold&#8482;",
  "brand": "Threshold",
  "price": "$90.00",
  "currency": "USD",
  "description": "Elevate your home aesthetics with this Ribbed Wood Wall Mirror from Threshold™. This wall mirror features a wooden frame with a wavy design, accentuated by a ribbed texture along the border that adds a flowy, elegant touch to your space. Best of all, it's easy to mount on the wall using pegs or screws.<br /><br />Threshold™: Looks like home, feels like you.",
  "categories": [
    "Home",
    "Home Decor",
    "Mirrors"
  ],
  "image_url": "https://target.scene7.com/is/image/Target/GUEST_51640d3b-6814-4a92-86b9-8152e66a15ea",
  "glb_url": "https://digitalcontent.target.com/vault/1754870400/CLOUD_4175e94d-185c-4f51-b03a-cbd6f209db25.glb",
  "product_url": "https://www.target.com/p/-/A-94568983",
  "dimensions": {
    "height": 0.7654,
    "width": 0.5139,
    "depth": 0.0308,
    "unit": "m",
    "source": "glb"
  }
}
