{
  "tcin": "94256803",
  "name": "24&#34;x36&#34; Textured Wall Mirror White - Threshold&#8482;",
  "brand": "Threshold",
  "price": "$63.00",
  "currency": "USD",
  "description": "Stylish and functional, this Textured Wall Mirror from Threshold™ makes an elegant addition to your home decor. This wall mirror features a textured wooden frame in white, making it simple to integrate into any decor scheme. Easy to mount on a wall, this rectangular mirror is perfect for your entryway, living room, bathroom, or bedroom, allowing you to check your appearance before heading out.<br /><br />Threshold™: Looks like home, feels like you.",
  "categories": [
    "Home",
    "Home Decor",
    "Mirrors"
  ],
  "image_url": "https://target.scene7.com/is/image/Target/GUEST_fe173891-de9b-427d-b066-13b868937195",
  "glb_url": "https://digitalcontent.target.com/vault/1756080000/CLOUD_3dc5a7f1-7751-4ec5-8c88-de5bc16c84db.glb",
  "product_url": "https://www.target.com/p/-/A-94256803",
  "dimensions": {
    "height": 0.9144,
    "width": 0.6096,
    "depth": 0.0406,
    "unit": "m",
    "source": "glb"
  },
  "color": "White",
  "color_source": "parsed"
}
