{
  "tcin": "83901180",
  "name": "6pc Plastic Drawer Organizer Clear - Brightroom&#8482;: Desk &#38; Office Organization Set, Clear Desk Drawer Organizers",
  "brand": "Brightroom",
  "price": "$12.00",
  "currency": "USD",
  "description": "Decluttering your drawers is fast and easy with this 6-Piece Plastic Drawer Organizer from Brightroom™. This set includes six bins in different sizes for storing different types of items, from staplers to post-its to paper clips. The bins fit easily into any drawer, and the translucent clear hue matches any color scheme while also letting you see what you've stored inside of each. Whether you work at home or in an office, this set of six drawer organizers is a smart and practical pick-up.<br /><br />Brightroom™: See your space in a new light.",
  "categories": [
    "School & Office Supplies",
    "Teacher Supplies & Classroom Decorations",
    "Teacher Supplies"
  ],
  "image_url": "https://target.scene7.com/is/image/Target/GUEST_ea47522d-50e3-428f-90de-32d06fa869cb",
  "glb_url": "https://digitalcontent.target.com/vault/1658361600/CLOUD_c68b4eed-201a-4379-bbf8-7e86decb7818.glb",
  "product_url": "https://www.target.com/p/-/A-83901180",
  "dimensions": {
    "height": 0.2286,
    "width": 0.1615,
    "depth": 0.1524,
    "unit": "m",
    "source": "glb"
  },
  "color": "Clear",
  "color_source": "parsed"
}
