{
  "tcin": "88050678",
  "name": "7.5&#39;x7.7&#39; Hexagon Macrame Outdoor Patio Market Umbrella Beige with Faux Wood Pole - Threshold&#8482;",
  "brand": "Threshold",
  "price": "$130.00",
  "currency": "USD",
  "description": "Stay comfortable by blocking out direct sun with this Hexagon Macrame Outdoor Patio Market Umbrella from Threshold™. Supported on a rust-resistant metal frame, this outdoor market umbrella features a hexagonal canopy made from soft fabric for helping you stay cool under the sun. Featuring a push-up lift type and equipped with a push-button tilt for more angles of shading, it features a macrame design in a beige hue with a fringed hem in white to add artistic flair to your patio, balcony or porch. Plus, it comes with a bag for easy carrying.<br /><br />Threshold™: Looks like home, feels like you.",
  "categories": [
    "Outdoor Living & Garden",
    "Outdoor Shade & Structures",
    "Patio Umbrellas",
    "Market Umbrellas"
  ],
  "image_url": "https://target.scene7.com/is/image/Target/GUEST_1f67f21b-87a5-43c4-b7dd-189d59a59009",
  "glb_url": "https://digitalcontent.target.com/vault/1702512000/CLOUD_bc2eac2e-b91d-455a-9982-cba514944583.glb",
  "product_url": "https://www.target.com/p/-/A-88050678",
  "dimensions": {
    "height": 2.2987,
    "width": 2.286,
    "depth": 2.0371,
    "unit": "m",
    "source": "glb"
  }
}
