{
  "tcin": "94688485",
  "name": "Arch Storage Ottoman - Hearth &#38; Hand&#8482; with Magnolia",
  "brand": "Hearth & Hand w/Magnolia Furniture",
  "price": "$129.99",
  "currency": "USD",
  "description": "Add style and functional storage to your home with this Arch Storage Ottoman from Hearth & Hand™ with Magnolia. Featuring a wooden frame with decorative arched detailing on the base, this storage ottoman stands 17.9 inches high. It showcases a round upholstered top that flips open to reveal a hidden storage space inside, perfect for stashing blankets, magazines or other living room essentials. This versatile piece works beautifully as a footrest or a coffee table.<br /><br />Hearth & Hand™ with Magnolia: Gather • Create • Enjoy<br /><br />Overall Width : Ø19.25 inches<br />Overall Depth : Ø19.25 inches<br />Overall Height : 18.75 inches<br />Distance Between Leg : Ø 8.5 inches<br />Base Width : Ø18.15 inches",
  "categories": [
    "Furniture",
    "Living Room Furniture",
    "Ottomans"
  ],
  "image_url": "https://target.scene7.com/is/image/Target/GUEST_9193e624-ad9c-4dae-8f51-5030fd255172",
  "glb_url": "https://digitalcontent.target.com/vault/1771891200/CLOUD_96ac2a39-03bd-445a-ae2b-73281e5de699.glb",
  "product_url": "https://www.target.com/p/-/A-94688485",
  "dimensions": {
    "height": 0.4743,
    "width": 0.4743,
    "depth": 0.4547,
    "unit": "m",
    "source": "glb"
  }
}
