{
  "tcin": "93668092",
  "name": "Candle Lamp Warmer Arched Gold and Black - Threshold&#8482;",
  "brand": "Threshold",
  "price": "$30.00",
  "currency": "USD",
  "description": "Set up your decor with a sophisticated piece using the Candle Lamp Warmer Arched Gold and Black from Threshold™. Designed to blend sleek style with cozy ambiance, this electric warmer gently heats jar candles using a halogen bulb rather than an open flame, releasing fragrance safely and evenly. Featuring a twist-lock bi-pin base (GU10) and an arched frame in a modern gold and black finish, it doubles as a stylish accent piece for any room. The glass lid complements the metal construction, creating a refined look that fits seamlessly into your decor while offering a flameless, fuss-free way to enjoy your favorite candles.<br /><br />Threshold™: Looks like home, feels like you™",
  "categories": [
    "Gift Ideas",
    "Gift Ideas for Her"
  ],
  "image_url": "https://target.scene7.com/is/image/Target/GUEST_5575e52b-3804-460c-bd08-27a52ecc3c6a",
  "glb_url": "https://digitalcontent.target.com/vault/1758672000/CLOUD_e367b9de-08a0-4af2-aabd-85390512890b.glb",
  "product_url": "https://www.target.com/p/-/A-93668092",
  "dimensions": {
    "height": 0.3112,
    "width": 0.2944,
    "depth": 0.181,
    "unit": "m",
    "source": "glb"
  }
}
