{
  "tcin": "90594397",
  "name": "Clysa Table Lamp - 21 Inch Height - TBL4502 - Black - Safavieh",
  "brand": "Safavieh",
  "price": "$67.99",
  "currency": "USD",
  "description": "Illuminate your space with the sleek and modern CLYSA table lamp. This 21 inch black iron lamp, paired with an elegant cotton shade, adds a touch of style to any room. The sturdy iron base offers a classic yet contemporary look that complements any decor. CLYSA provides the right amount of light for your late-night reading or to create a cozy atmosphere. Its simple yet sophisticated design makes it a versatile piece, easily fitting into both traditional and modern settings. Whether placed on a bedside table or a living room shelf, this lamp is designed to meet your lighting needs. Discover how CLYSA can transform your space into a haven of comfort and style.",
  "categories": [
    "Home",
    "Home Decor",
    "Lamps & Lighting",
    "Desk Lamps"
  ],
  "image_url": "https://target.scene7.com/is/image/Target/GUEST_728c78b2-865a-42db-a7d0-fb5f9d03e3c9",
  "glb_url": "https://digitalcontent.target.com/vault/1763683200/CLOUD_eaa8bd17-3275-454f-8c34-43483ceac4c8.glb",
  "product_url": "https://www.target.com/p/-/A-90594397",
  "dimensions": {
    "height": 0.5374,
    "width": 0.2754,
    "depth": 0.2754,
    "unit": "m",
    "source": "glb"
  },
  "color": "Black",
  "color_source": "parsed"
}
