{
  "tcin": "91065193",
  "name": "Dasheen Leaf Potted Artificial Plant - Room Essentials&#8482;",
  "brand": "Room Essentials",
  "price": "$12.75",
  "currency": "USD",
  "description": "Add a natural charm to your indoor space with this Dasheen Leaf Potted Artificial Plant from Room Essentials™. This artificial arrangement features a realistic-looking dasheen leaf tree, and it comes housed in a white melamine pot with styrofoam filler for instant display. Place it on a side or console table with other real or faux plants to create a relaxing indoor garden.<br /><br />Room Essentials™: Everyday Value",
  "categories": [
    "Home",
    "Home Decor",
    "Artificial Greenery",
    "Artificial Plants"
  ],
  "image_url": "https://target.scene7.com/is/image/Target/GUEST_8b07c699-40e2-4726-966a-0c5592b5db1b",
  "glb_url": "https://digitalcontent.target.com/vault/1744848000/CLOUD_be53400b-93b5-4d85-aa64-adb187f24e81.glb",
  "product_url": "https://www.target.com/p/-/A-91065193",
  "dimensions": {
    "height": 0.381,
    "width": 0.2847,
    "depth": 0.2605,
    "unit": "m",
    "source": "glb"
  }
}
