{
  "tcin": "94420016",
  "name": "Open Weave LED Medium Outdoor Lantern Beige - Threshold&#8482;",
  "brand": "Threshold",
  "price": "$50.00",
  "currency": "USD",
  "description": "Elevate your patio or pathway lighting with this Open-Weave LED Medium Outdoor Lantern from Threshold™. Made from metal and resin, this beige-color outdoor lantern features an open-weave design in an oval shape and is equipped with a bright LED bulb. Solar/battery powered, it has a base slide switch and also features convenient, automated dusk on/dawn off settings.<br /><br />Threshold™: Looks like home, feels like you.",
  "categories": [
    "Outdoor Living & Garden",
    "Outdoor Lighting",
    "Outdoor Lamps"
  ],
  "image_url": "https://target.scene7.com/is/image/Target/GUEST_72ff0d08-62c0-416b-934c-768232428556",
  "glb_url": "https://digitalcontent.target.com/vault/1756166400/CLOUD_d816abfe-4c43-4bbb-b3a5-3bb329c3c4b4.glb",
  "product_url": "https://www.target.com/p/-/A-94420016",
  "color": "Beige",
  "color_source": "parsed",
  "dimensions": {
    "height": 0.5106,
    "width": 0.2542,
    "depth": 0.2542,
    "unit": "m",
    "source": "glb"
  }
}
