{
  "tcin": "52806273",
  "name": "Pelham Nightstand White - Threshold&#8482;",
  "brand": "Threshold",
  "price": "$200.00",
  "currency": "USD",
  "description": "The Pelham Nightstand White from Threshold is both modern and functional. This space-saving bedside table gives you three full-size drawers, all perfect for storing the odds and ends of your life out of sight. Use the sturdy profiled top to pile on your books, cell phone, alarm clock, lamp and whatever else you like; this nightstand can take it with style to spare. It's built with a strong wood frame for durability and long-lasting use.<br /><br />If you’re not satisfied with any Target Owned Brand item, return it within one year with a receipt for an exchange or a refund.",
  "categories": [
    "Furniture",
    "Bedroom Furniture",
    "Nightstands"
  ],
  "image_url": "https://target.scene7.com/is/image/Target/GUEST_a5490db6-8936-4363-8b15-2889074f6e68",
  "glb_url": "https://digitalcontent.target.com/vault/1626220800/CLOUD_5bbf7cf8-0f83-4bcb-96a6-9cb8b24af013.glb",
  "product_url": "https://www.target.com/p/-/A-52806273",
  "color": "White",
  "color_source": "parsed",
  "dimensions": {
    "height": 0.6599,
    "width": 0.5999,
    "depth": 0.4572,
    "unit": "m",
    "source": "glb"
  }
}
