{
  "tcin": "89811870",
  "name": "Plastic Storage Cabinet - Brightroom&#8482;",
  "brand": "Brightroom",
  "price": "$75.00",
  "currency": "USD",
  "description": "Maintain a neat and tidy space while keeping things organized with the Plastic Storage Cabinet from Brightroom™. Designed in a vertical alignment, this storage cabinet features multiple shelves to help provide ample space for items in your bathroom, home office or any other space. Plus, it also has two doors to help keep items securely out of sight.<br /><br />Brightroom™: See your space in a new light.",
  "categories": [
    "Home",
    "Storage & Organization",
    "Garage Storage"
  ],
  "image_url": "https://target.scene7.com/is/image/Target/GUEST_8712496a-d1d4-407b-ac34-80b22240e4aa",
  "glb_url": "https://digitalcontent.target.com/vault/1719964800/CLOUD_291042a7-faa0-4770-ab86-35113b00b6b8.glb",
  "product_url": "https://www.target.com/p/-/A-89811870",
  "dimensions": {
    "height": 0.9155,
    "width": 0.6452,
    "depth": 0.4895,
    "unit": "m",
    "source": "glb"
  }
}
