{
  "tcin": "92247874",
  "name": "Printed Tennis Dog Ball Toy - Boots &#38; Barkley&#8482; - 3pk",
  "brand": "Boots & Barkley",
  "price": "$2.99",
  "currency": "USD",
  "description": "Update your pet's toy collection with the 3-Pack of Printed Tennis Dog Ball Toy from Boots & Barkley™. This dog toy set includes three tennis balls in varying colors for fun and energetic play. Made of rubber and designed for small and medium breeds, the balls are perfect for playing fetch in your backyard or at the park.<br /><br />Boots & Barkley™: Because pets are just the best.<br /><br />100% satisfaction guaranteed or your money back.",
  "categories": [
    "Pets",
    "Dog Supplies",
    "Dog Toys"
  ],
  "image_url": "https://target.scene7.com/is/image/Target/GUEST_b5217950-5329-4ee5-ae58-ca574fa842fe",
  "glb_url": "https://digitalcontent.target.com/vault/1770076800/CLOUD_c9a61c7d-1c8d-4327-a13d-2de4486eef29.glb",
  "product_url": "https://www.target.com/p/-/A-92247874",
  "dimensions": {
    "height": 0.2336,
    "width": 0.0635,
    "depth": 0.0635,
    "unit": "m",
    "source": "glb"
  }
}
