{
  "tcin": "93370920",
  "name": "Rechargeable Battery Bluetooth Speaker - dealworthy&#8482; Black: Portable, Wireless USB Connection",
  "brand": "Dealworthy",
  "price": "$4.99",
  "currency": "USD",
  "description": "Bring the beats wherever you go with the Rechargeable Battery Bluetooth Speaker from dealworthy™ in Black. With a 33 ft. wireless range and up to 4 hours of battery life, it’s perfect for backyard hangs, small gatherings or solo jam sessions. Compact yet powerful, this speaker is your go-to for music on the move.<br /><br />dealworthy™: Just what you need, priced just right.™",
  "categories": [
    "Electronics",
    "Speakers & Audio Systems",
    "Bluetooth Speakers"
  ],
  "image_url": "https://target.scene7.com/is/image/Target/GUEST_a8a74274-9a11-411a-8868-13583fe0e15d",
  "glb_url": "https://digitalcontent.target.com/vault/1743897600/CLOUD_fb6cefc9-20cd-42f9-acdf-f22cb68d81f2.glb",
  "product_url": "https://www.target.com/p/-/A-93370920",
  "dimensions": {
    "height": 0.0856,
    "width": 0.0854,
    "depth": 0.0358,
    "unit": "m",
    "source": "glb"
  }
}
