{
  "tcin": "91652579",
  "name": "Round Faux Rattan Kids&#39; Lamp with Pleated Floral Shade - Pillowfort&#8482;",
  "brand": "Pillowfort",
  "price": "$35.00",
  "currency": "USD",
  "description": "Beautifully decorate and light up your kid's space with the Round Faux-Rattan Lamp with Pleated Floral Shade from Pillowfort™. This round table lamp features a faux-rattan round base that complements the pleated floral shade for a delightful look they'll love. Designed with a one-way light setting, this table lamp is easy to turn on and off with the socket push-through switch.",
  "categories": [
    "Home",
    "Home Decor",
    "Lamps & Lighting",
    "Desk Lamps"
  ],
  "image_url": "https://target.scene7.com/is/image/Target/GUEST_492500b9-f266-4e77-bc3f-42ca70696495",
  "glb_url": "https://digitalcontent.target.com/vault/1744070400/CLOUD_6ee79410-bab5-4387-8168-b93b9ffd0c71.glb",
  "product_url": "https://www.target.com/p/-/A-91652579",
  "dimensions": {
    "height": 0.3302,
    "width": 0.2582,
    "depth": 0.2582,
    "unit": "m",
    "source": "glb"
  }
}
