{
  "tcin": "88117512",
  "name": "(Set of 2) 16&#34; x 20&#34; Painterly Collage Framed Under Glass Wall Art Prints  - Threshold&#8482;: Modern Abstract Art, Sawtooth Back",
  "brand": "Threshold",
  "price": "$45.50",
  "currency": "USD",
  "description": "Make a bold statement in any room with this (Set of 2) 16\" x 20\" Painterly Collage Framed Wall Art from Threshold™. These framed wall art pieces feature lively colors, adding an instant pop of creativity to your space. The natural frames provide a touch of rustic charm while complementing your décor. Easy to hang and wonderful to admire, the (Set of 2) 16\" x 20\" Painterly Collage Framed Wall Art from Threshold™ are the perfect way to refresh your space.<br /><br />Threshold™: Looks like home, feels like you.<br />",
  "categories": [
    "Home",
    "Home Decor",
    "Wall Decor",
    "Wall Art",
    "Framed Wall Art"
  ],
  "image_url": "https://target.scene7.com/is/image/Target/GUEST_bf57abf0-a5c2-4e2a-9cd7-8d1686208fee",
  "glb_url": "https://digitalcontent.target.com/vault/1683590400/CLOUD_aec53fd1-7337-45ce-b5ea-6723ecb3b309.glb",
  "product_url": "https://www.target.com/p/-/A-88117512",
  "dimensions": {
    "height": 0.839,
    "width": 0.5087,
    "depth": 0.0303,
    "unit": "m",
    "source": "glb"
  }
}
