{
  "tcin": "94685778",
  "name": "Square Floral Pillow - Threshold&#8482;",
  "brand": "Threshold",
  "price": "$25.00",
  "currency": "USD",
  "description": "Bring springtime charm to your living space with this Square Floral Throw Pillow from Threshold™. This decorative throw pillow is made from cotton-linen blend fabric with polyester filling to offer cushioned comfort on any bed, sofa or armchair. Featuring vibrant floral print, it also has striped flange for added visual interest.<br /><br />Threshold™: Looks like home, feels like you.",
  "categories": [
    "Home",
    "Home Decor",
    "Throw Pillows"
  ],
  "image_url": "https://target.scene7.com/is/image/Target/GUEST_3e38443b-cd54-4fd8-9274-0c97d57a5e4c",
  "glb_url": "https://digitalcontent.target.com/vault/1764547200/CLOUD_f79e6f20-06f1-4d7c-b10c-b3b681c2cef0.glb",
  "product_url": "https://www.target.com/p/-/A-94685778",
  "dimensions": {
    "height": 0.5284,
    "width": 0.4659,
    "depth": 0.188,
    "unit": "m",
    "source": "glb"
  }
}
