{
  "tcin": "81212630",
  "name": "Tabletop Easel - Mondo Llama&#8482;: Off-White Hardwood Artist Stand for Painting, 16.8&#34; Height, No Assembly Required",
  "brand": "Mondo Llama",
  "price": "$5.00",
  "currency": "USD",
  "description": "The Wood Easel from Mondo Llama™ is a must-have art essential to be used during a painting sesh or after a masterpiece is complete. In a natural finish, this wooden easel can be left as is to allow your finished artwork to shine, or jazzed up with paint, stickers or stencils for an extra touch of artistic flair. The tabletop design makes it easy to set up your craft station when you're ready to paint or draw, as well as place on any flat surface for display when you're done! <br /><br />Make it bright. Make it bold. Make it up. And most of all, make it you. Find your creativity in the making with Mondo Llama.",
  "categories": [
    "Home",
    "Arts, Crafts & Sewing",
    "Art & Craft Furniture"
  ],
  "image_url": "https://target.scene7.com/is/image/Target/GUEST_f6ad33b2-43ff-4fa2-bbd9-7de12c1919cb",
  "glb_url": "https://digitalcontent.target.com/vault/1647561600/CLOUD_c31ad0ba-5221-46bb-ab43-6a6c33e72c7d.glb",
  "product_url": "https://www.target.com/p/-/A-81212630",
  "dimensions": {
    "height": 0.4267,
    "width": 0.2007,
    "depth": 0.1935,
    "unit": "m",
    "source": "glb"
  }
}
