{
  "tcin": "81646310",
  "name": "Tropical Leaves Peel &#38; Stick Wallpaper Pink - Opalhouse&#8482;: Removable Vinyl, Botanical Leaf Pattern, Self-Adhesive, 27.5 Sq Ft Coverage",
  "brand": "Opalhouse",
  "price": "$34.00",
  "currency": "USD",
  "description": "You'll love the bright style your home takes on with the Tropical Leaves Peel and Stick Wallpaper from Opalhouse™. This wallpaper has a bold pattern of palm leaves in bright shades of pink against a white backdrop, making it a fun pick for livening up a kitchen, bedroom or a living room accent wall. The wallpaper has an adhesive back that makes it easy as can be to apply — simply cut the needed amount, peel off the backing and stick to the wall with none of the mess or fuss of traditional wallpaper. One roll provides enough for 27.5 square feet of space, and the wallpaper has a vinyl finish that's easy to keep clean.<br /><br />This is your house. Where you create spaces as bold as your spirit. Collect objects as inspired as your dreams. Find pieces that remind you of every place you’ve been. Discover stories to inspire everywhere you have yet to go. This is Opalhouse.",
  "categories": [
    "Home",
    "Home Improvement",
    "Wallpaper"
  ],
  "image_url": "https://target.scene7.com/is/image/Target/GUEST_2043c5c7-65ab-4ab3-bf52-a21288eb13b9",
  "glb_url": "https://digitalcontent.target.com/vault/1673481600/CLOUD_49374b7c-53ea-4996-b6fe-464a7f05dc6c.glb",
  "product_url": "https://www.target.com/p/-/A-81646310",
  "color": "Pink",
  "color_source": "parsed",
  "dimensions": {
    "height": 5.0292,
    "width": 0.508,
    "depth": 0.0003,
    "unit": "m",
    "source": "glb"
  }
}
