{
  "tcin": "89981650",
  "name": "Turtle Pull Along Toy - Gigglescape&#8482;: Silicone, 18+ Months, Problem Solving, Fine Motor Skills, No Assembly, 4 Pieces",
  "brand": "Gigglescape",
  "price": "$15.00",
  "currency": "USD",
  "description": "Your little one can practice movement their way with the Turtle Pull-Along Toy from Gigglescape™. This pull-along toy includes four turtles of different colors and sizes that stack and attach in a train they can pull around. The turtles' heads move while rolling for extra charm, and they are nestable for easy storage after playtime.<br /><br />Gigglescape™: Where play starts and discovery never ends.",
  "categories": [
    "Toys",
    "Learning & Educational Toys",
    "Learning & Development Toys"
  ],
  "image_url": "https://target.scene7.com/is/image/Target/GUEST_0b8e4d39-1711-498c-b479-9b329ebcd32c",
  "glb_url": "https://digitalcontent.target.com/vault/1737331200/CLOUD_9b0c1d20-0068-489c-aee0-456814a4e6c4.glb",
  "product_url": "https://www.target.com/p/-/A-89981650",
  "dimensions": {
    "height": 0.3048,
    "width": 0.2758,
    "depth": 0.1596,
    "unit": "m",
    "source": "glb"
  }
}
