{
  "tcin": "83342793",
  "name": "Wall Mounted Drying Rack White - Brightroom&#8482;: Folding Pull-Out Steel, 36.42&#34; Height, 10lb Capacity, Adult Assembly Required",
  "brand": "Brightroom",
  "price": "$37.00",
  "currency": "USD",
  "description": "With the Wall-Mounted Drying Rack from Brightroom™, it's easy to add extra hanging space for air-drying laundry in your home. This easy-to-open, wall-mounted drying rack instantly adds more space in your laundry room or elsewhere for hanging your clothes, linens and more to dry, while its convenient space-saving construction allows it to fold up flat against the wall when not in use. Rust-resistant carbon steel and rubberwood materials provide a stylish and practical design, while a 25.2-inch by 36.42-inch side adds plenty of space for air-drying a variety of garments.<br /><br />Brightroom™ started with a simple truth: When you’ve got it together, you feel better. Our versatile designs reveal the possibility in every closet, cupboard and drawer, and work together to create brilliant ways to organize your every day.",
  "categories": [
    "Home",
    "Storage & Organization",
    "Laundry Room Organization",
    "Clothes Drying"
  ],
  "image_url": "https://target.scene7.com/is/image/Target/GUEST_f615ea45-3522-40c6-950b-6e39debe464e",
  "glb_url": "https://digitalcontent.target.com/vault/1668384000/CLOUD_a03b0281-034e-41c6-8c68-10609f077fb0.glb",
  "product_url": "https://www.target.com/p/-/A-83342793",
  "color": "White",
  "color_source": "parsed",
  "dimensions": {
    "height": 0.9251,
    "width": 0.6401,
    "depth": 0.0661,
    "unit": "m",
    "source": "glb"
  }
}
