{
  "tcin": "81644430",
  "name": "Woven and Glass Toothbrush Holder - Threshold&#8482;",
  "brand": "Threshold",
  "price": "$13.00",
  "currency": "USD",
  "description": "Bring boho charm to your bathroom space with this Woven and Glass Toothbrush Holder from Threshold™. Featuring a glass tumbler held inside a woven frame with raffia-like accents, this toothbrush holder lends artistic flair to your decor. The round, open top design makes it easy to pick up and place your toothpaste, toothbrushes and other items. Place it on any flat surface in your bathroom with a coordinating woven and glass soap pump to create a beautiful setting.",
  "categories": [
    "Home",
    "Bath",
    "Bathroom Accessories"
  ],
  "image_url": "https://target.scene7.com/is/image/Target/GUEST_ac96d67c-fade-481d-84d2-9430b1c4edd0",
  "glb_url": "https://digitalcontent.target.com/vault/1668384000/CLOUD_453c34a3-0e22-4846-a9bd-9adfe73d3c0a.glb",
  "product_url": "https://www.target.com/p/-/A-81644430",
  "dimensions": {
    "height": 0.1082,
    "width": 0.0832,
    "depth": 0.0831,
    "unit": "m",
    "source": "glb"
  }
}
