{
  "scale_px_per_m": 38.3268,
  "products": [
    {
      "item_no": "90590490",
      "name": "STOCKHOLM 2025 vase",
      "color": "brown",
      "categories": [
        "Home decor & accessories",
        "Vases & decorating bowls"
      ],
      "price": "39.99",
      "currency": "USD",
      "width": 10,
      "depth": 8,
      "elevation": 10
    },
    {
      "item_no": "70593814",
      "name": "STOCKHOLM 2025 rug, flatwoven",
      "color": "white/brown/light blue handwoven",
      "categories": [
        "Rugs & home textiles",
        "Rugs"
      ],
      "price": "599.99",
      "currency": "USD",
      "width": 93,
      "depth": 1,
      "elevation": 135
    },
    {
      "item_no": "60586692",
      "name": "STOCKHOLM 2025 glass-door cabinet",
      "color": "oak veneer",
      "categories": [
        "Storage & organization",
        "Display & storage cabinets"
      ],
      "price": "399",
      "currency": "USD",
      "width": 33,
      "depth": 16,
      "elevation": 39
    },
    {
      "item_no": "60593782",
      "name": "STOCKHOLM 2025 chair",
      "color": "dark brown/leather",
      "categories": [
        "Tables & chairs",
        "Dining furniture",
        "Dining chairs"
      ],
      "price": "225",
      "currency": "USD",
      "width": 22,
      "depth": 20,
      "elevation": 29
    },
    {
      "item_no": "40608242",
      "name": "BERGSHYTTAN table",
      "color": "dark brown ash veneer",
      "categories": [
        "Tables & chairs",
        "Dining furniture",
        "Dining tables"
      ],
      "price": "449.99",
      "currency": "USD",
      "width": 36,
      "depth": 29,
      "elevation": 92
    }
  ]
}